<annotation>
  <folder>kitti</folder>
  <filename>000637.png</filename>
  <source>
    <database>kitti Database</database>
    <annotation>kitti</annotation>
    <image>flickr</image>
    <flickrid>-1</flickrid>
  </source>
  <owner>
    <flickrid>muke</flickrid>
    <name>muke</name>
  </owner>
  <size>
    <width>1224</width>
    <height>370</height>
    <depth>3</depth>
  </size>
  <segmented>0</segmented>
  <object>
    <name>Car</name>
    <pose>Unspecified</pose>
    <truncated>1</truncated>
    <difficult>0</difficult>
    <bndbox>
      <xmin>124</xmin>
      <ymin>180</ymin>
      <xmax>273</xmax>
      <ymax>242</ymax>
    </bndbox>
  </object>
  <object>
    <name>Car</name>
    <pose>Unspecified</pose>
    <truncated>1</truncated>
    <difficult>0</difficult>
    <bndbox>
      <xmin>1032</xmin>
      <ymin>184</ymin>
      <xmax>1223</xmax>
      <ymax>369</ymax>
    </bndbox>
  </object>
  <object>
    <name>Car</name>
    <pose>Unspecified</pose>
    <truncated>1</truncated>
    <difficult>0</difficult>
    <bndbox>
      <xmin>802</xmin>
      <ymin>176</ymin>
      <xmax>1122</xmax>
      <ymax>360</ymax>
    </bndbox>
  </object>
  <object>
    <name>Car</name>
    <pose>Unspecified</pose>
    <truncated>1</truncated>
    <difficult>0</difficult>
    <bndbox>
      <xmin>729</xmin>
      <ymin>177</ymin>
      <xmax>854</xmax>
      <ymax>267</ymax>
    </bndbox>
  </object>
  <object>
    <name>Car</name>
    <pose>Unspecified</pose>
    <truncated>1</truncated>
    <difficult>0</difficult>
    <bndbox>
      <xmin>694</xmin>
      <ymin>177</ymin>
      <xmax>783</xmax>
      <ymax>240</ymax>
    </bndbox>
  </object>
  <object>
    <name>Car</name>
    <pose>Unspecified</pose>
    <truncated>1</truncated>
    <difficult>0</difficult>
    <bndbox>
      <xmin>681</xmin>
      <ymin>175</ymin>
      <xmax>741</xmax>
      <ymax>220</ymax>
    </bndbox>
  </object>
  <object>
    <name>Car</name>
    <pose>Unspecified</pose>
    <truncated>1</truncated>
    <difficult>0</difficult>
    <bndbox>
      <xmin>663</xmin>
      <ymin>174</ymin>
      <xmax>707</xmax>
      <ymax>210</ymax>
    </bndbox>
  </object>
  <object>
    <name>Car</name>
    <pose>Unspecified</pose>
    <truncated>1</truncated>
    <difficult>0</difficult>
    <bndbox>
      <xmin>560</xmin>
      <ymin>171</ymin>
      <xmax>583</xmax>
      <ymax>188</ymax>
    </bndbox>
  </object>
</annotation>
