<annotation>
  <folder>kitti</folder>
  <filename>000904.png</filename>
  <source>
    <database>kitti Database</database>
    <annotation>kitti</annotation>
    <image>flickr</image>
    <flickrid>-1</flickrid>
  </source>
  <owner>
    <flickrid>muke</flickrid>
    <name>muke</name>
  </owner>
  <size>
    <width>1242</width>
    <height>375</height>
    <depth>3</depth>
  </size>
  <segmented>0</segmented>
  <object>
    <name>Car</name>
    <pose>Unspecified</pose>
    <truncated>1</truncated>
    <difficult>0</difficult>
    <bndbox>
      <xmin>584</xmin>
      <ymin>185</ymin>
      <xmax>617</xmax>
      <ymax>211</ymax>
    </bndbox>
  </object>
  <object>
    <name>Car</name>
    <pose>Unspecified</pose>
    <truncated>1</truncated>
    <difficult>0</difficult>
    <bndbox>
      <xmin>532</xmin>
      <ymin>182</ymin>
      <xmax>561</xmax>
      <ymax>205</ymax>
    </bndbox>
  </object>
  <object>
    <name>Van</name>
    <pose>Unspecified</pose>
    <truncated>1</truncated>
    <difficult>0</difficult>
    <bndbox>
      <xmin>599</xmin>
      <ymin>170</ymin>
      <xmax>620</xmax>
      <ymax>198</ymax>
    </bndbox>
  </object>
  <object>
    <name>Car</name>
    <pose>Unspecified</pose>
    <truncated>1</truncated>
    <difficult>0</difficult>
    <bndbox>
      <xmin>237</xmin>
      <ymin>179</ymin>
      <xmax>303</xmax>
      <ymax>211</ymax>
    </bndbox>
  </object>
</annotation>
