<annotation>
  <folder>kitti</folder>
  <filename>003228.png</filename>
  <source>
    <database>kitti Database</database>
    <annotation>kitti</annotation>
    <image>flickr</image>
    <flickrid>-1</flickrid>
  </source>
  <owner>
    <flickrid>muke</flickrid>
    <name>muke</name>
  </owner>
  <size>
    <width>1242</width>
    <height>375</height>
    <depth>3</depth>
  </size>
  <segmented>0</segmented>
  <object>
    <name>Car</name>
    <pose>Unspecified</pose>
    <truncated>1</truncated>
    <difficult>0</difficult>
    <bndbox>
      <xmin>651</xmin>
      <ymin>179</ymin>
      <xmax>793</xmax>
      <ymax>272</ymax>
    </bndbox>
  </object>
  <object>
    <name>Car</name>
    <pose>Unspecified</pose>
    <truncated>1</truncated>
    <difficult>0</difficult>
    <bndbox>
      <xmin>566</xmin>
      <ymin>169</ymin>
      <xmax>666</xmax>
      <ymax>212</ymax>
    </bndbox>
  </object>
  <object>
    <name>Car</name>
    <pose>Unspecified</pose>
    <truncated>1</truncated>
    <difficult>0</difficult>
    <bndbox>
      <xmin>736</xmin>
      <ymin>166</ymin>
      <xmax>850</xmax>
      <ymax>217</ymax>
    </bndbox>
  </object>
  <object>
    <name>Car</name>
    <pose>Unspecified</pose>
    <truncated>1</truncated>
    <difficult>0</difficult>
    <bndbox>
      <xmin>821</xmin>
      <ymin>164</ymin>
      <xmax>918</xmax>
      <ymax>207</ymax>
    </bndbox>
  </object>
  <object>
    <name>Car</name>
    <pose>Unspecified</pose>
    <truncated>1</truncated>
    <difficult>0</difficult>
    <bndbox>
      <xmin>903</xmin>
      <ymin>166</ymin>
      <xmax>976</xmax>
      <ymax>201</ymax>
    </bndbox>
  </object>
  <object>
    <name>Car</name>
    <pose>Unspecified</pose>
    <truncated>1</truncated>
    <difficult>0</difficult>
    <bndbox>
      <xmin>949</xmin>
      <ymin>157</ymin>
      <xmax>1033</xmax>
      <ymax>197</ymax>
    </bndbox>
  </object>
</annotation>
