<annotation>
  <folder>kitti</folder>
  <filename>005981.png</filename>
  <source>
    <database>kitti Database</database>
    <annotation>kitti</annotation>
    <image>flickr</image>
    <flickrid>-1</flickrid>
  </source>
  <owner>
    <flickrid>muke</flickrid>
    <name>muke</name>
  </owner>
  <size>
    <width>1241</width>
    <height>376</height>
    <depth>3</depth>
  </size>
  <segmented>0</segmented>
  <object>
    <name>Car</name>
    <pose>Unspecified</pose>
    <truncated>1</truncated>
    <difficult>0</difficult>
    <bndbox>
      <xmin>625</xmin>
      <ymin>178</ymin>
      <xmax>699</xmax>
      <ymax>245</ymax>
    </bndbox>
  </object>
  <object>
    <name>Car</name>
    <pose>Unspecified</pose>
    <truncated>1</truncated>
    <difficult>0</difficult>
    <bndbox>
      <xmin>0</xmin>
      <ymin>200</ymin>
      <xmax>193</xmax>
      <ymax>313</ymax>
    </bndbox>
  </object>
  <object>
    <name>Car</name>
    <pose>Unspecified</pose>
    <truncated>1</truncated>
    <difficult>0</difficult>
    <bndbox>
      <xmin>435</xmin>
      <ymin>179</ymin>
      <xmax>494</xmax>
      <ymax>223</ymax>
    </bndbox>
  </object>
  <object>
    <name>Car</name>
    <pose>Unspecified</pose>
    <truncated>1</truncated>
    <difficult>0</difficult>
    <bndbox>
      <xmin>466</xmin>
      <ymin>183</ymin>
      <xmax>511</xmax>
      <ymax>214</ymax>
    </bndbox>
  </object>
  <object>
    <name>Van</name>
    <pose>Unspecified</pose>
    <truncated>1</truncated>
    <difficult>0</difficult>
    <bndbox>
      <xmin>51</xmin>
      <ymin>172</ymin>
      <xmax>217</xmax>
      <ymax>251</ymax>
    </bndbox>
  </object>
  <object>
    <name>Car</name>
    <pose>Unspecified</pose>
    <truncated>1</truncated>
    <difficult>0</difficult>
    <bndbox>
      <xmin>693</xmin>
      <ymin>185</ymin>
      <xmax>727</xmax>
      <ymax>209</ymax>
    </bndbox>
  </object>
  <object>
    <name>Car</name>
    <pose>Unspecified</pose>
    <truncated>1</truncated>
    <difficult>0</difficult>
    <bndbox>
      <xmin>764</xmin>
      <ymin>184</ymin>
      <xmax>795</xmax>
      <ymax>201</ymax>
    </bndbox>
  </object>
</annotation>
