<annotation>
  <folder>kitti</folder>
  <filename>007060.png</filename>
  <source>
    <database>kitti Database</database>
    <annotation>kitti</annotation>
    <image>flickr</image>
    <flickrid>-1</flickrid>
  </source>
  <owner>
    <flickrid>muke</flickrid>
    <name>muke</name>
  </owner>
  <size>
    <width>1242</width>
    <height>375</height>
    <depth>3</depth>
  </size>
  <segmented>0</segmented>
  <object>
    <name>Car</name>
    <pose>Unspecified</pose>
    <truncated>1</truncated>
    <difficult>0</difficult>
    <bndbox>
      <xmin>539</xmin>
      <ymin>184</ymin>
      <xmax>791</xmax>
      <ymax>292</ymax>
    </bndbox>
  </object>
  <object>
    <name>Car</name>
    <pose>Unspecified</pose>
    <truncated>1</truncated>
    <difficult>0</difficult>
    <bndbox>
      <xmin>440</xmin>
      <ymin>168</ymin>
      <xmax>695</xmax>
      <ymax>278</ymax>
    </bndbox>
  </object>
  <object>
    <name>Van</name>
    <pose>Unspecified</pose>
    <truncated>1</truncated>
    <difficult>0</difficult>
    <bndbox>
      <xmin>45</xmin>
      <ymin>180</ymin>
      <xmax>143</xmax>
      <ymax>245</ymax>
    </bndbox>
  </object>
  <object>
    <name>Car</name>
    <pose>Unspecified</pose>
    <truncated>1</truncated>
    <difficult>0</difficult>
    <bndbox>
      <xmin>295</xmin>
      <ymin>186</ymin>
      <xmax>349</xmax>
      <ymax>220</ymax>
    </bndbox>
  </object>
  <object>
    <name>Car</name>
    <pose>Unspecified</pose>
    <truncated>1</truncated>
    <difficult>0</difficult>
    <bndbox>
      <xmin>434</xmin>
      <ymin>187</ymin>
      <xmax>627</xmax>
      <ymax>260</ymax>
    </bndbox>
  </object>
</annotation>
